redshift_sqlalchemy
