Metadata-Version: 1.1
Name: redshift-sqlalchemy
Version: 0.3.3
Summary: Amazon Redshift Dialect for sqlalchemy
Home-page: https://github.com/binarydud/redshift_sqlalchemy
Author: Matt George
Author-email: mgeorge@gmail.com
License: MIT
Platform: UNKNOWN
Classifier: Development Status :: 4 - Beta
Classifier: Environment :: Console
Classifier: Intended Audience :: Developers
Classifier: License :: OSI Approved :: MIT License
Classifier: Operating System :: OS Independent
Classifier: Programming Language :: Python
